otelize/__init__.py
otelize/adapters/__init__.py
otelize/adapters/otel_value_converter.py
otelize/infra/__init__.py
otelize/infra/config.py
otelize/infra/tracer.py
otelize/instrumenters/__init__.py
otelize/instrumenters/decorators/__init__.py
otelize/instrumenters/decorators/otelize.py
otelize/instrumenters/decorators/span_filler.py
otelize/instrumenters/wrappers/__init__.py
otelize/instrumenters/wrappers/otelize_context_manager.py
otelize/instrumenters/wrappers/otelize_iterable.py
otelize/tests/__init__.py
otelize/tests/base_otel_test_case.py
otelize/tests/infra/__init__.py
otelize/tests/infra/test_config.py
otelize/tests/instrumenters/__init__.py
otelize/tests/instrumenters/decorators/__init__.py
otelize/tests/instrumenters/decorators/otelize/__init__.py
otelize/tests/instrumenters/decorators/otelize/base_otelize_test_case.py
otelize/tests/instrumenters/decorators/otelize/dummy_calculator.py
otelize/tests/instrumenters/decorators/otelize/test_otelize_on_class.py
otelize/tests/instrumenters/decorators/otelize/test_otelize_on_function.py
otelize/tests/instrumenters/wrappers/__init__.py
otelize/tests/instrumenters/wrappers/test_otelize_context_manager.py
otelize/tests/instrumenters/wrappers/test_otelize_iterable.py
otelize-0.4.1.dist-info/licenses/LICENSE
otelize-0.4.1.dist-info/METADATA
otelize-0.4.1.dist-info/WHEEL
otelize-0.4.1.dist-info/top_level.txt
otelize-0.4.1.dist-info/RECORD
