Metadata-Version: 2.4
Name: otelize
Version: 0.4.1
Summary: A Python decorator to add OTEL auto-instrumentation to your functions
Author-email: "Diego J. Romero López" <diegojromerolopez@gmail.com>
Project-URL: repository, https://github.com/diegojromerolopez/otelize
Project-URL: documentation, https://otelize.readthedocs.io/en/latest/
Project-URL: Bug Tracker, https://github.com/diegojromerolopez/otelize/issues
Keywords: telemetry,OTEL,auto-instrumentation,decorator
Classifier: Programming Language :: Python :: Implementation :: CPython
Classifier: Programming Language :: Python :: Implementation :: PyPy
Classifier: Programming Language :: Python :: 3.10
Classifier: Programming Language :: Python :: 3.11
Classifier: Programming Language :: Python :: 3.12
Classifier: Programming Language :: Python :: 3.13
Classifier: Programming Language :: Python :: 3.14
Classifier: Topic :: Software Development :: Libraries
Classifier: Development Status :: 3 - Alpha
Classifier: License :: OSI Approved :: MIT License
Requires-Python: >=3.10
License-File: LICENSE
Requires-Dist: opentelemetry-api>=1.36.0
Dynamic: license-file
